{
    "транзакции": [
        {
            "дата": "07.11.2025 16:57",
            "тип": "доход",
            "категория": "💼 Зарплата",
            "сумма": 123.0,
            "описание": "Аванс",
            "счет": "Наличные"
        },
        {
            "дата": "07.11.2025 16:58",
            "тип": "расход",
            "категория": "🥕 Рынок",
            "сумма": 12.0,
            "описание": "Продукты",
            "счет": "Наличные"
        }
    ],
    "наличные": 111.0,
    "карта": 0
}